xlsxdocument/__init__.py
xlsxdocument/document.py
xlsxdocument-1.3.10.dist-info/LICENSE
xlsxdocument-1.3.10.dist-info/METADATA
xlsxdocument-1.3.10.dist-info/WHEEL
xlsxdocument-1.3.10.dist-info/top_level.txt
xlsxdocument-1.3.10.dist-info/RECORD
