Metadata-Version: 2.1
Name: xlsxdocument
Version: 1.3.10
Summary: Easily create XLSX documents with Django
Home-page: https://github.com/matthiask/xlsxdocument/
Author: Matthias Kestenholz
Author-email: mk@feinheit.ch
License-File: LICENSE
